neurequa/__init__.py
neurequa/artefact_detections.py
neurequa/cognitive_module.py
neurequa/neuralynx_io.py
neurequa/quality_module.py
neurequa-0.1.1.18.dist-info/LICENSE
neurequa-0.1.1.18.dist-info/METADATA
neurequa-0.1.1.18.dist-info/WHEEL
neurequa-0.1.1.18.dist-info/top_level.txt
neurequa-0.1.1.18.dist-info/RECORD
